cloudrail/terraform_0_13/__init__.py
cloudrail/terraform_0_13/terraform
cloudrail_terraform_0_13-0.33.0.dist-info/METADATA
cloudrail_terraform_0_13-0.33.0.dist-info/WHEEL
cloudrail_terraform_0_13-0.33.0.dist-info/top_level.txt
cloudrail_terraform_0_13-0.33.0.dist-info/RECORD
